mopidy_syncprojects/__init__.py
mopidy_syncprojects/actor.py
mopidy_syncprojects/ext.conf
mopidy_syncprojects/library.py
mopidy_syncprojects/syncprojects.py
Mopidy_Syncprojects-0.0.3.dist-info/LICENSE
Mopidy_Syncprojects-0.0.3.dist-info/METADATA
Mopidy_Syncprojects-0.0.3.dist-info/WHEEL
Mopidy_Syncprojects-0.0.3.dist-info/entry_points.txt
Mopidy_Syncprojects-0.0.3.dist-info/top_level.txt
Mopidy_Syncprojects-0.0.3.dist-info/RECORD
